[
  {
    "id": 7801,
    "type": 3,
    "lat": 46.926409,
    "lon": 28.899151,
    "elevation": 418,
    "frequency": 11370,
    "range": 200,
    "icao": null,
    "identifier": "CHN",
    "runwayNumber": null,
    "name": "CHISINAU VOR/DME",
    "variation": 5.2,
    "bearing": 0,
    "bias": 0
  },
  {
    "id": 13191,
    "type": 4,
    "lat": 46.928336,
    "lon": 28.957869,
    "elevation": 399,
    "frequency": 11030,
    "range": 18,
    "icao": "LUKK",
    "identifier": "IRG",
    "runwayNumber": "08",
    "name": "ILS-cat-I",
    "variation": null,
    "bearing": 88.326,
    "bias": 0
  },
  {
    "id": 13192,
    "type": 4,
    "lat": 46.927256,
    "lon": 28.904411,
    "elevation": 399,
    "frequency": 10990,
    "range": 18,
    "icao": "LUKK",
    "identifier": "ILD",
    "runwayNumber": "26",
    "name": "ILS-cat-I",
    "variation": null,
    "bearing": 268.285,
    "bias": 0
  },
  {
    "id": 16691,
    "type": 6,
    "lat": 46.926422,
    "lon": 28.912025,
    "elevation": 399,
    "frequency": 11030,
    "range": 10,
    "icao": "LUKK",
    "identifier": "IRG",
    "runwayNumber": "08",
    "name": "GS",
    "variation": null,
    "bearing": 300088.305,
    "bias": 0
  },
  {
    "id": 16692,
    "type": 6,
    "lat": 46.927214,
    "lon": 28.951217,
    "elevation": 399,
    "frequency": 10990,
    "range": 10,
    "icao": "LUKK",
    "identifier": "ILD",
    "runwayNumber": "26",
    "name": "GS",
    "variation": null,
    "bearing": 300268.305,
    "bias": 0
  },
  {
    "id": 22203,
    "type": 12,
    "lat": 46.926422,
    "lon": 28.912025,
    "elevation": 397,
    "frequency": 11030,
    "range": 18,
    "icao": "LUKK",
    "identifier": "IRG",
    "runwayNumber": "08",
    "name": "DME-ILS",
    "variation": null,
    "bearing": 0,
    "bias": 0.2
  },
  {
    "id": 22204,
    "type": 12,
    "lat": 46.927214,
    "lon": 28.951217,
    "elevation": 286,
    "frequency": 10990,
    "range": 18,
    "icao": "LUKK",
    "identifier": "ILD",
    "runwayNumber": "26",
    "name": "DME-ILS",
    "variation": null,
    "bearing": 0,
    "bias": 0.1
  },
  {
    "id": 23282,
    "type": 12,
    "lat": 46.926409,
    "lon": 28.899151,
    "elevation": 418,
    "frequency": 11370,
    "range": 200,
    "icao": null,
    "identifier": null,
    "runwayNumber": null,
    "name": null,
    "variation": null,
    "bearing": 0,
    "bias": 0
  }
]