[
  {
    "lat": 47.879891667,
    "lon": -123.475833333,
    "name": "ARRIE ENRT K1",
    "id": 135077
  },
  {
    "lat": 47.148041667,
    "lon": -123.40955,
    "name": "ELMAA ENRT K1",
    "id": 138385
  },
  {
    "lat": 47.194166667,
    "lon": -123.222777778,
    "name": "FALDA ENRT K1",
    "id": 138700
  },
  {
    "lat": 47.080833333,
    "lon": -123.218888889,
    "name": "FEPOT ENRT K1",
    "id": 138830
  },
  {
    "lat": 47.243333333,
    "lon": -123.040833333,
    "name": "HAROB ENRT K1",
    "id": 140028
  },
  {
    "lat": 47,
    "lon": -124,
    "name": "KS12C ENRT K1",
    "id": 142928
  },
  {
    "lat": 47.5,
    "lon": -124,
    "name": "KS15C ENRT K1",
    "id": 142934
  },
  {
    "lat": 47.070691667,
    "lon": -123.696963889,
    "name": "OZALU ENRT K1",
    "id": 145539
  },
  {
    "lat": 47.163105556,
    "lon": -123.353169444,
    "name": "SANDR ENRT K1",
    "id": 147110
  },
  {
    "lat": 47.976788889,
    "lon": -123.150016667,
    "name": "TNSND ENRT K1",
    "id": 148528
  },
  {
    "lat": 47.131827778,
    "lon": -123.470041667,
    "name": "ULESS ENRT K1",
    "id": 148917
  },
  {
    "lat": 47.221930556,
    "lon": -123.131661111,
    "name": "WONKU ENRT K1",
    "id": 150222
  },
  {
    "lat": 47.019430556,
    "lon": -123.537613889,
    "name": "COXOD KHQM K1",
    "id": 169344
  },
  {
    "lat": 47.006525,
    "lon": -123.645572222,
    "name": "LAMMB KHQM K1",
    "id": 169349
  },
  {
    "lat": 47.217086111,
    "lon": -123.227344444,
    "name": "30THR KSHN K1",
    "id": 184433
  },
  {
    "lat": 47.210272222,
    "lon": -123.231622222,
    "name": "ALARE KSHN K1",
    "id": 184434
  },
  {
    "lat": 47.197430556,
    "lon": -123.277861111,
    "name": "IMINE KSHN K1",
    "id": 184435
  },
  {
    "lat": 47.268891667,
    "lon": -123.019425,
    "name": "PORSY KSHN K1",
    "id": 184438
  },
  {
    "lat": 47.431305556,
    "lon": -123.189588889,
    "name": "EMDEN KTCM K1",
    "id": 186270
  },
  {
    "lat": 47.231394444,
    "lon": -123.063775,
    "name": "WAKEN KTCM K1",
    "id": 186297
  }
]