[
  {
    "type": 1,
    "icao": "CYBX",
    "lat": 51.4421065,
    "lon": -2.8716459999999984,
    "communications": [],
    "elevation": 121,
    "tower": false,
    "name": "LOURDES DE BLANC SABLON",
    "runways": [
      {
        "type": 100,
        "width": 45.72,
        "surfaceType": null,
        "numberStart": "05",
        "numberEnd": "23",
        "latStart": 51.436644,
        "lonStart": -57.190861,
        "latEnd": 51.447569,
        "lonEnd": -57.181761,
        "length": 0,
        "surfacetype": 1
      }
    ],
    "id": 14640
  },
  {
    "type": 1,
    "icao": "CYAY",
    "lat": 51.3919,
    "lon": -2.3494530000000005,
    "communications": [
      {
        "type": 50,
        "frequency": 11865,
        "name": "AWOS1"
      },
      {
        "type": 51,
        "frequency": 12230,
        "name": "CTAF"
      }
    ],
    "elevation": 108,
    "tower": false,
    "name": "ST ANTHONY",
    "runways": [
      {
        "type": 100,
        "width": 30.48,
        "surfaceType": null,
        "numberStart": "10",
        "numberEnd": "28",
        "latStart": 51.390931,
        "lonStart": -56.091775,
        "latEnd": 51.392869,
        "lonEnd": -56.074519,
        "length": 0,
        "surfacetype": 1
      }
    ],
    "id": 22452
  }
]