[
  {
    "type": 17,
    "icao": "VA29",
    "lat": 38.45484861,
    "lon": -78.01360862,
    "communications": [],
    "elevation": 475,
    "tower": false,
    "name": "[H] Culpeper Memorial Hospital",
    "runways": [
      {
        "type": 102,
        "width": 9.1,
        "surfaceType": 2,
        "numberStart": "H1",
        "numberEnd": null,
        "latStart": 38.45484861,
        "lonStart": -78.01360862,
        "latEnd": null,
        "lonEnd": null,
        "length": 9.1
      }
    ],
    "id": 29204
  },
  {
    "type": 17,
    "icao": "6VA8",
    "lat": 38.04069361,
    "lon": -78.75613195,
    "communications": [],
    "elevation": 722,
    "tower": false,
    "name": "[H] Mirador",
    "runways": [
      {
        "type": 102,
        "width": 15.2,
        "surfaceType": 1,
        "numberStart": "H1",
        "numberEnd": null,
        "latStart": 38.04069361,
        "lonStart": -78.75613195,
        "latEnd": null,
        "lonEnd": null,
        "length": 15.2
      }
    ],
    "id": 31392
  },
  {
    "type": 17,
    "icao": "5VA6",
    "lat": 38.48429,
    "lon": -78.86780445,
    "communications": [],
    "elevation": 1500,
    "tower": false,
    "name": "[H] Rockingham",
    "runways": [
      {
        "type": 102,
        "width": 15.2,
        "surfaceType": 3,
        "numberStart": "H1",
        "numberEnd": null,
        "latStart": 38.48429,
        "lonStart": -78.86780445,
        "latEnd": null,
        "lonEnd": null,
        "length": 15.2
      }
    ],
    "id": 32393
  },
  {
    "type": 17,
    "icao": "8VA5",
    "lat": 38.03277777,
    "lon": -78.49973417,
    "communications": [],
    "elevation": 490,
    "tower": false,
    "name": "[H] University of Virginia Hospital",
    "runways": [
      {
        "type": 102,
        "width": 19.5,
        "surfaceType": 2,
        "numberStart": "H1",
        "numberEnd": null,
        "latStart": 38.03277777,
        "lonStart": -78.49973417,
        "latEnd": null,
        "lonEnd": null,
        "length": 19.5
      }
    ],
    "id": 33522
  }
]