[
  {
    "type": 1,
    "icao": "SCKM",
    "lat": -41.482952455,
    "lon": -72.30758098999999,
    "communications": [],
    "elevation": 129,
    "tower": false,
    "name": "CochamC3",
    "runways": [
      {
        "type": 100,
        "width": 20.12,
        "surfaceType": null,
        "numberStart": "17",
        "numberEnd": "35",
        "latStart": -41.4798555,
        "lonStart": -72.30735356,
        "latEnd": -41.48604941,
        "lonEnd": -72.30780842,
        "length": 0,
        "surfacetype": 4
      }
    ],
    "id": 5141
  },
  {
    "type": 1,
    "icao": "SCCK",
    "lat": -41.800038,
    "lon": -72.72133657500001,
    "communications": [],
    "elevation": 15,
    "tower": false,
    "name": "Contao",
    "runways": [
      {
        "type": 100,
        "width": 17.98,
        "surfaceType": null,
        "numberStart": "06",
        "numberEnd": "24",
        "latStart": -41.8017739,
        "lonStart": -72.72409111,
        "latEnd": -41.7983021,
        "lonEnd": -72.71858204,
        "length": 0,
        "surfacetype": 5
      }
    ],
    "id": 5275
  },
  {
    "type": 1,
    "icao": "SCPV",
    "lat": -41.349219585,
    "lon": -72.946835745,
    "communications": [],
    "elevation": 426,
    "tower": false,
    "name": "El Mirador",
    "runways": [
      {
        "type": 100,
        "width": 17.98,
        "surfaceType": null,
        "numberStart": "15",
        "numberEnd": "33",
        "latStart": -41.34593603,
        "lonStart": -72.94848662,
        "latEnd": -41.35250314,
        "lonEnd": -72.94518487,
        "length": 0,
        "surfacetype": 1
      }
    ],
    "id": 7043
  },
  {
    "type": 1,
    "icao": "SCPF",
    "lat": -41.45424379666667,
    "lon": -72.91782182666667,
    "communications": [
      {
        "type": 54,
        "frequency": 12730,
        "name": "INFO"
      }
    ],
    "elevation": 367,
    "tower": true,
    "name": "Marcel Marchant",
    "runways": [
      {
        "type": 100,
        "width": 10.06,
        "surfaceType": null,
        "numberStart": "01",
        "numberEnd": "19",
        "latStart": -41.45858156,
        "lonStart": -72.92013014,
        "latEnd": -41.45035999,
        "lonEnd": -72.91524613,
        "length": 0,
        "surfacetype": 1
      },
      {
        "type": 102,
        "width": 9.1,
        "surfaceType": 1,
        "numberStart": "H1",
        "numberEnd": null,
        "latStart": -41.45378984,
        "lonStart": -72.91808921,
        "latEnd": null,
        "lonEnd": null,
        "length": 9.1
      }
    ],
    "id": 16660
  },
  {
    "type": 1,
    "icao": "SCPU",
    "lat": -41.05411893,
    "lon": -72.008300695,
    "communications": [],
    "elevation": 899,
    "tower": false,
    "name": "Peulla",
    "runways": [
      {
        "type": 100,
        "width": 17.98,
        "surfaceType": null,
        "numberStart": "02",
        "numberEnd": "20",
        "latStart": -41.05650615,
        "lonStart": -72.01077481,
        "latEnd": -41.05173171,
        "lonEnd": -72.00582658,
        "length": 0,
        "surfacetype": 3
      }
    ],
    "id": 20036
  },
  {
    "type": 1,
    "icao": "SCPB",
    "lat": -41.65848200000001,
    "lon": -72.299881065,
    "communications": [],
    "elevation": 62,
    "tower": false,
    "name": "Puelo Bajo",
    "runways": [
      {
        "type": 100,
        "width": 17.98,
        "surfaceType": null,
        "numberStart": "05",
        "numberEnd": "23",
        "latStart": -41.65968491,
        "lonStart": -72.30322206,
        "latEnd": -41.65727909,
        "lonEnd": -72.29654007,
        "length": 0,
        "surfacetype": 2
      }
    ],
    "id": 20592
  },
  {
    "type": 1,
    "icao": "SCRN",
    "lat": -41.9617585,
    "lon": -72.45297450000001,
    "communications": [],
    "elevation": 29,
    "tower": false,
    "name": "RC-o Negro",
    "runways": [
      {
        "type": 100,
        "width": 17.98,
        "surfaceType": null,
        "numberStart": "02",
        "numberEnd": "20",
        "latStart": -41.964427,
        "lonStart": -72.455404,
        "latEnd": -41.95909,
        "lonEnd": -72.450545,
        "length": 0,
        "surfacetype": 1
      }
    ],
    "id": 21887
  }
]