[
  {
    "type": 1,
    "icao": "DNAA",
    "lat": 9.006790500000001,
    "lon": 7.2631716950000005,
    "communications": [
      {
        "type": 50,
        "frequency": 12705,
        "name": "ATIS"
      },
      {
        "type": 50,
        "frequency": 12390,
        "name": "ATIS"
      },
      {
        "type": 50,
        "frequency": 12750,
        "name": "ATIS"
      },
      {
        "type": 54,
        "frequency": 11980,
        "name": "TWR"
      },
      {
        "type": 55,
        "frequency": 12790,
        "name": "APP"
      },
      {
        "type": 55,
        "frequency": 11980,
        "name": "APP"
      }
    ],
    "elevation": 1123,
    "tower": true,
    "name": "NNAMDI AZIKIWE INTL",
    "runways": [
      {
        "type": 100,
        "width": 44.81,
        "surfaceType": null,
        "numberStart": "04",
        "numberEnd": "22",
        "latStart": 8.99346998,
        "lonStart": 7.25375932,
        "latEnd": 9.02011102,
        "lonEnd": 7.27258407,
        "length": 0,
        "surfacetype": 1
      }
    ],
    "id": 16035
  }
]