[
  {
    "type": 1,
    "icao": "DN51",
    "lat": 7.4572375,
    "lon": 6.461129,
    "communications": [],
    "elevation": 620,
    "tower": false,
    "name": "AJAOKUTA",
    "runways": [
      {
        "type": 100,
        "width": 45.11,
        "surfaceType": null,
        "numberStart": "06",
        "numberEnd": "24",
        "latStart": 7.453494,
        "lonStart": 6.455361,
        "latEnd": 7.460981,
        "lonEnd": 6.466897,
        "length": 0,
        "surfacetype": 1
      }
    ],
    "id": 16029
  }
]