[
  {
    "lat": -24.717,
    "lon": -49.152,
    "name": "DOMIN",
    "id": 35245
  },
  {
    "lat": -24.07,
    "lon": -49.139833,
    "name": "GALES",
    "id": 46014
  },
  {
    "lat": -24.9495,
    "lon": -49.693333,
    "name": "GARCI",
    "id": 46210
  },
  {
    "lat": -24.818333,
    "lon": -49.155,
    "name": "MADRI",
    "id": 74388
  },
  {
    "lat": -24.153667,
    "lon": -49.6395,
    "name": "MINOT",
    "id": 77651
  },
  {
    "lat": -24.367,
    "lon": -49.147,
    "name": "MORLU",
    "id": 79121
  }
]