[
  {
    "lat": 45.829897222,
    "lon": -122.611902778,
    "name": "AASEN ENRT K1",
    "id": 134645
  },
  {
    "lat": 45.833136111,
    "lon": -122.131047222,
    "name": "AXQOX ENRT K1",
    "id": 135219
  },
  {
    "lat": 45.604019444,
    "lon": -122.847736111,
    "name": "BEAST ENRT K1",
    "id": 135477
  },
  {
    "lat": 45.433016667,
    "lon": -122.310819444,
    "name": "BISLE ENRT K1",
    "id": 135731
  },
  {
    "lat": 45.310569444,
    "lon": -122.764891667,
    "name": "CANBY ENRT K1",
    "id": 136402
  },
  {
    "lat": 45.062172222,
    "lon": -122.152463889,
    "name": "CHISM ENRT K1",
    "id": 136757
  },
  {
    "lat": 45.541030556,
    "lon": -122.325177778,
    "name": "COSUG ENRT K1",
    "id": 137159
  },
  {
    "lat": 45.349886111,
    "lon": -122.363725,
    "name": "CUKIS ENRT K1",
    "id": 137350
  },
  {
    "lat": 45.830027778,
    "lon": -122.384372222,
    "name": "DMAZH ENRT K1",
    "id": 137845
  },
  {
    "lat": 45.790705556,
    "lon": -122.361466667,
    "name": "DMBOR ENRT K1",
    "id": 137846
  },
  {
    "lat": 45.651694444,
    "lon": -122.918691667,
    "name": "DUDRE ENRT K1",
    "id": 138101
  },
  {
    "lat": 45.643063889,
    "lon": -122.463325,
    "name": "EMZEY ENRT K1",
    "id": 138445
  },
  {
    "lat": 45.432225,
    "lon": -122.901263889,
    "name": "ENDZZ ENRT K1",
    "id": 138461
  },
  {
    "lat": 45.759883333,
    "lon": -122.757258333,
    "name": "EYAVU ENRT K1",
    "id": 138642
  },
  {
    "lat": 45.249222222,
    "lon": -122.642997222,
    "name": "FLOWR ENRT K1",
    "id": 139020
  },
  {
    "lat": 45.277891667,
    "lon": -122.603152778,
    "name": "GLARA ENRT K1",
    "id": 139508
  },
  {
    "lat": 45.104372222,
    "lon": -122.845625,
    "name": "GNNET ENRT K1",
    "id": 139575
  },
  {
    "lat": 45.7415,
    "lon": -122.238666667,
    "name": "GYMME ENRT K1",
    "id": 139872
  },
  {
    "lat": 45.489427778,
    "lon": -122.276833333,
    "name": "HADIS ENRT K1",
    "id": 139905
  },
  {
    "lat": 45.198227778,
    "lon": -122.214152778,
    "name": "HARZL ENRT K1",
    "id": 140046
  },
  {
    "lat": 45.462425,
    "lon": -122.8681,
    "name": "INTLL ENRT K1",
    "id": 140932
  },
  {
    "lat": 45.164347222,
    "lon": -122.050769444,
    "name": "JJACE ENRT K1",
    "id": 141453
  },
  {
    "lat": 45.674319444,
    "lon": -122.812638889,
    "name": "KELYY ENRT K1",
    "id": 142064
  },
  {
    "lat": 45.765827778,
    "lon": -122.84015,
    "name": "MAHKE ENRT K1",
    "id": 143998
  },
  {
    "lat": 45.115083333,
    "lon": -122.607130556,
    "name": "MAVER ENRT K1",
    "id": 144123
  },
  {
    "lat": 45.222036111,
    "lon": -122.968777778,
    "name": "MINNE ENRT K1",
    "id": 144352
  },
  {
    "lat": 45.090697222,
    "lon": -122.426186111,
    "name": "MRTEN ENRT K1",
    "id": 144603
  },
  {
    "lat": 45.452919444,
    "lon": -122.59885,
    "name": "MULES ENRT K1",
    "id": 144642
  },
  {
    "lat": 45.465283333,
    "lon": -122.620808333,
    "name": "OCITY ENRT K1",
    "id": 145155
  },
  {
    "lat": 45.911866667,
    "lon": -122.176597222,
    "name": "OJUMU ENRT K1",
    "id": 145262
  },
  {
    "lat": 45.913372222,
    "lon": -122.564638889,
    "name": "OKARE ENRT K1",
    "id": 145265
  },
  {
    "lat": 45.648452778,
    "lon": -122.160541667,
    "name": "OKKOR ENRT K1",
    "id": 145269
  },
  {
    "lat": 45.422527778,
    "lon": -122.720738889,
    "name": "OSWEG ENRT K1",
    "id": 145447
  },
  {
    "lat": 45.617141667,
    "lon": -122.671572222,
    "name": "PEGTY ENRT K1",
    "id": 145736
  },
  {
    "lat": 45.743666667,
    "lon": -122.353616667,
    "name": "PIQRI ENRT K1",
    "id": 145925
  },
  {
    "lat": 45.103994444,
    "lon": -122.121861111,
    "name": "PUTZZ ENRT K1",
    "id": 146318
  },
  {
    "lat": 45.235644444,
    "lon": -122.794316667,
    "name": "RAWER ENRT K1",
    "id": 146479
  },
  {
    "lat": 45.567930556,
    "lon": -122.472833333,
    "name": "RIVRR ENRT K1",
    "id": 146731
  },
  {
    "lat": 45.911972222,
    "lon": -122.632347222,
    "name": "ROARK ENRT K1",
    "id": 146770
  },
  {
    "lat": 45.541597222,
    "lon": -122.893177778,
    "name": "TOSEH ENRT K1",
    "id": 148596
  },
  {
    "lat": 45.647583333,
    "lon": -122.937591667,
    "name": "WANOS ENRT K1",
    "id": 149726
  },
  {
    "lat": 45.549844444,
    "lon": -122.959061111,
    "name": "CFVNT KHIO K1",
    "id": 168832
  },
  {
    "lat": 45.409594444,
    "lon": -122.970030556,
    "name": "CIGOP KHIO K1",
    "id": 168833
  },
  {
    "lat": 45.393055556,
    "lon": -122.841666667,
    "name": "EMELY KHIO K1",
    "id": 168837
  },
  {
    "lat": 45.452697222,
    "lon": -122.963802778,
    "name": "EYODA KHIO K1",
    "id": 168838
  },
  {
    "lat": 45.452463889,
    "lon": -122.960847222,
    "name": "EYOHE KHIO K1",
    "id": 168839
  },
  {
    "lat": 45.445536111,
    "lon": -122.833741667,
    "name": "GERDD KHIO K1",
    "id": 168841
  },
  {
    "lat": 45.500775,
    "lon": -122.956858333,
    "name": "HINTS KHIO K1",
    "id": 168843
  },
  {
    "lat": 45.114663889,
    "lon": -122.503994444,
    "name": "HOBGU KHIO K1",
    "id": 168844
  },
  {
    "lat": 45.544744444,
    "lon": -122.969783333,
    "name": "MA127 KHIO K1",
    "id": 168847
  },
  {
    "lat": 45.533988889,
    "lon": -122.952052778,
    "name": "MEMLE KHIO K1",
    "id": 168848
  },
  {
    "lat": 45.376511111,
    "lon": -122.778375,
    "name": "NNIKE KHIO K1",
    "id": 168849
  },
  {
    "lat": 45.508222222,
    "lon": -122.916072222,
    "name": "ZABAX KHIO K1",
    "id": 168852
  },
  {
    "lat": 45.303963889,
    "lon": -122.900988889,
    "name": "OZIER KMMV K1",
    "id": 175834
  },
  {
    "lat": 45.377369444,
    "lon": -122.850202778,
    "name": "TOCBU KMMV K1",
    "id": 175837
  },
  {
    "lat": 45.281086111,
    "lon": -122.951563889,
    "name": "UNECE KMMV K1",
    "id": 175838
  },
  {
    "lat": 45.565916667,
    "lon": -122.547836111,
    "name": "30TAC KPDX K1",
    "id": 179834
  },
  {
    "lat": 45.531627778,
    "lon": -122.458752778,
    "name": "ADDUM KPDX K1",
    "id": 179836
  },
  {
    "lat": 45.76735,
    "lon": -122.925669444,
    "name": "ANINE KPDX K1",
    "id": 179837
  },
  {
    "lat": 45.558055556,
    "lon": -122.486944444,
    "name": "ANTNA KPDX K1",
    "id": 179838
  },
  {
    "lat": 45.758333333,
    "lon": -122.745694444,
    "name": "ARUPT KPDX K1",
    "id": 179839
  },
  {
    "lat": 45.584152778,
    "lon": -122.568280556,
    "name": "BACUP KPDX K1",
    "id": 179840
  },
  {
    "lat": 45.747788889,
    "lon": -122.591558333,
    "name": "BATYL KPDX K1",
    "id": 179841
  },
  {
    "lat": 45.577586111,
    "lon": -122.823322222,
    "name": "BBREW KPDX K1",
    "id": 179842
  },
  {
    "lat": 45.643505556,
    "lon": -122.7209,
    "name": "BLAZR KPDX K1",
    "id": 179843
  },
  {
    "lat": 45.697575,
    "lon": -122.860661111,
    "name": "BUXOM KPDX K1",
    "id": 179845
  },
  {
    "lat": 45.478391667,
    "lon": -122.425825,
    "name": "BYKES KPDX K1",
    "id": 179846
  },
  {
    "lat": 45.567077778,
    "lon": -122.441255556,
    "name": "CATMI KPDX K1",
    "id": 179847
  },
  {
    "lat": 45.715519444,
    "lon": -122.763691667,
    "name": "CATUL KPDX K1",
    "id": 179848
  },
  {
    "lat": 45.497569444,
    "lon": -122.357902778,
    "name": "CF28L KPDX K1",
    "id": 179849
  },
  {
    "lat": 45.477563889,
    "lon": -122.296033333,
    "name": "CF28R KPDX K1",
    "id": 179850
  },
  {
    "lat": 45.598438889,
    "lon": -122.604947222,
    "name": "CFBGC KPDX K1",
    "id": 179851
  },
  {
    "lat": 45.501369444,
    "lon": -122.470636111,
    "name": "CFBHP KPDX K1",
    "id": 179852
  },
  {
    "lat": 45.608613889,
    "lon": -122.447130556,
    "name": "CFBHQ KPDX K1",
    "id": 179853
  },
  {
    "lat": 45.594177778,
    "lon": -122.506044444,
    "name": "CFBHR KPDX K1",
    "id": 179854
  },
  {
    "lat": 45.497572222,
    "lon": -122.485727778,
    "name": "CFBHS KPDX K1",
    "id": 179855
  },
  {
    "lat": 45.586913889,
    "lon": -122.522105556,
    "name": "CFBJH KPDX K1",
    "id": 179856
  },
  {
    "lat": 45.607441667,
    "lon": -122.775713889,
    "name": "CFFVS KPDX K1",
    "id": 179857
  },
  {
    "lat": 45.684305556,
    "lon": -122.715166667,
    "name": "CFFVT KPDX K1",
    "id": 179858
  },
  {
    "lat": 45.688033333,
    "lon": -122.712225,
    "name": "CFFWG KPDX K1",
    "id": 179859
  },
  {
    "lat": 45.614891667,
    "lon": -122.769858333,
    "name": "CFFWH KPDX K1",
    "id": 179860
  },
  {
    "lat": 45.692227778,
    "lon": -122.600186111,
    "name": "CIZZL KPDX K1",
    "id": 179861
  },
  {
    "lat": 45.658333333,
    "lon": -122.7725,
    "name": "CNFLU KPDX K1",
    "id": 179862
  },
  {
    "lat": 45.713422222,
    "lon": -122.429455556,
    "name": "COVDU KPDX K1",
    "id": 179863
  },
  {
    "lat": 45.800305556,
    "lon": -122.304463889,
    "name": "CREAK KPDX K1",
    "id": 179864
  },
  {
    "lat": 45.724630556,
    "lon": -122.683119444,
    "name": "DAYSS KPDX K1",
    "id": 179865
  },
  {
    "lat": 45.565086111,
    "lon": -122.469788889,
    "name": "DIKKE KPDX K1",
    "id": 179866
  },
  {
    "lat": 45.549683333,
    "lon": -122.170380556,
    "name": "DLILE KPDX K1",
    "id": 179867
  },
  {
    "lat": 45.745544444,
    "lon": -122.737588889,
    "name": "DOUHH KPDX K1",
    "id": 179868
  },
  {
    "lat": 45.476797222,
    "lon": -122.438836111,
    "name": "DSHUT KPDX K1",
    "id": 179869
  },
  {
    "lat": 45.560772222,
    "lon": -122.358633333,
    "name": "EJAYE KPDX K1",
    "id": 179870
  },
  {
    "lat": 45.563994444,
    "lon": -122.485386111,
    "name": "EVIDE KPDX K1",
    "id": 179871
  },
  {
    "lat": 45.535580556,
    "lon": -122.463363889,
    "name": "FF28L KPDX K1",
    "id": 179872
  },
  {
    "lat": 45.342502778,
    "lon": -122.693991667,
    "name": "FFULL KPDX K1",
    "id": 179873
  },
  {
    "lat": 45.596466667,
    "lon": -122.597575,
    "name": "FISUM KPDX K1",
    "id": 179874
  },
  {
    "lat": 45.603452778,
    "lon": -122.826930556,
    "name": "GAMBE KPDX K1",
    "id": 179875
  },
  {
    "lat": 45.677072222,
    "lon": -122.832725,
    "name": "HAIRN KPDX K1",
    "id": 179877
  },
  {
    "lat": 45.507261111,
    "lon": -122.396583333,
    "name": "HANAH KPDX K1",
    "id": 179878
  },
  {
    "lat": 45.560066667,
    "lon": -122.362525,
    "name": "HHOPZ KPDX K1",
    "id": 179879
  },
  {
    "lat": 45.577577778,
    "lon": -122.802772222,
    "name": "HOMOG KPDX K1",
    "id": 179880
  },
  {
    "lat": 45.471822222,
    "lon": -122.306411111,
    "name": "HPSTR KPDX K1",
    "id": 179881
  },
  {
    "lat": 45.6664,
    "lon": -122.496858333,
    "name": "HUDUT KPDX K1",
    "id": 179882
  },
  {
    "lat": 45.567963889,
    "lon": -122.526805556,
    "name": "HULAB KPDX K1",
    "id": 179883
  },
  {
    "lat": 45.9309,
    "lon": -122.488397222,
    "name": "HYKER KPDX K1",
    "id": 179884
  },
  {
    "lat": 45.410847222,
    "lon": -122.381516667,
    "name": "ICEAX KPDX K1",
    "id": 179886
  },
  {
    "lat": 45.615177778,
    "lon": -122.672969444,
    "name": "JADNU KPDX K1",
    "id": 179887
  },
  {
    "lat": 45.620363889,
    "lon": -122.661297222,
    "name": "JALAG KPDX K1",
    "id": 179888
  },
  {
    "lat": 45.628755556,
    "lon": -122.5507,
    "name": "JAXAG KPDX K1",
    "id": 179889
  },
  {
    "lat": 45.471944444,
    "lon": -122.306880556,
    "name": "LEZLI KPDX K1",
    "id": 179891
  },
  {
    "lat": 45.830055556,
    "lon": -122.456294444,
    "name": "LIQWD KPDX K1",
    "id": 179892
  },
  {
    "lat": 45.575763889,
    "lon": -122.575308333,
    "name": "MA28L KPDX K1",
    "id": 179894
  },
  {
    "lat": 45.643116667,
    "lon": -122.806372222,
    "name": "MIVUE KPDX K1",
    "id": 179895
  },
  {
    "lat": 45.560577778,
    "lon": -122.516175,
    "name": "MUBAE KPDX K1",
    "id": 179896
  },
  {
    "lat": 45.530036111,
    "lon": -122.797063889,
    "name": "MYCRO KPDX K1",
    "id": 179897
  },
  {
    "lat": 45.483561111,
    "lon": -122.311477778,
    "name": "NACIY KPDX K1",
    "id": 179899
  },
  {
    "lat": 45.767866667,
    "lon": -122.809580556,
    "name": "NNUTT KPDX K1",
    "id": 179900
  },
  {
    "lat": 45.512413889,
    "lon": -122.434466667,
    "name": "NOLGE KPDX K1",
    "id": 179901
  },
  {
    "lat": 45.783880556,
    "lon": -122.328138889,
    "name": "NULRE KPDX K1",
    "id": 179902
  },
  {
    "lat": 45.511119444,
    "lon": -122.381594444,
    "name": "OMMSI KPDX K1",
    "id": 179903
  },
  {
    "lat": 45.572222222,
    "lon": -122.394444444,
    "name": "PAAPR KPDX K1",
    "id": 179904
  },
  {
    "lat": 45.627119444,
    "lon": -122.678597222,
    "name": "PORTA KPDX K1",
    "id": 179905
  },
  {
    "lat": 45.643908333,
    "lon": -122.747011111,
    "name": "POWLZ KPDX K1",
    "id": 179906
  },
  {
    "lat": 45.623561111,
    "lon": -122.928472222,
    "name": "PUBBB KPDX K1",
    "id": 179908
  },
  {
    "lat": 45.563608333,
    "lon": -122.54055,
    "name": "PULOE KPDX K1",
    "id": 179909
  },
  {
    "lat": 45.472522222,
    "lon": -122.181258333,
    "name": "REEDI KPDX K1",
    "id": 179910
  },
  {
    "lat": 45.715177778,
    "lon": -122.757791667,
    "name": "RIPPP KPDX K1",
    "id": 179912
  },
  {
    "lat": 45.443425,
    "lon": -122.468344444,
    "name": "ROAGE KPDX K1",
    "id": 179913
  },
  {
    "lat": 45.668044444,
    "lon": -122.809363889,
    "name": "SAUVI KPDX K1",
    "id": 179914
  },
  {
    "lat": 45.542775,
    "lon": -122.040319444,
    "name": "SHAFR KPDX K1",
    "id": 179915
  },
  {
    "lat": 45.555158333,
    "lon": -122.263075,
    "name": "SHYNE KPDX K1",
    "id": 179916
  },
  {
    "lat": 45.616730556,
    "lon": -122.193319444,
    "name": "SOOZN KPDX K1",
    "id": 179917
  },
  {
    "lat": 45.415555556,
    "lon": -122.734055556,
    "name": "SSAIL KPDX K1",
    "id": 179918
  },
  {
    "lat": 45.603847222,
    "lon": -122.272708333,
    "name": "SSDEE KPDX K1",
    "id": 179919
  },
  {
    "lat": 45.617644444,
    "lon": -122.389066667,
    "name": "SSSUN KPDX K1",
    "id": 179920
  },
  {
    "lat": 45.462841667,
    "lon": -122.253255556,
    "name": "TAMAR KPDX K1",
    "id": 179921
  },
  {
    "lat": 45.623152778,
    "lon": -122.366377778,
    "name": "THEID KPDX K1",
    "id": 179922
  },
  {
    "lat": 45.535441667,
    "lon": -122.443636111,
    "name": "TOLOC KPDX K1",
    "id": 179924
  },
  {
    "lat": 45.592533333,
    "lon": -122.831127778,
    "name": "TOWWN KPDX K1",
    "id": 179925
  },
  {
    "lat": 45.667686111,
    "lon": -122.7833,
    "name": "TRAYL KPDX K1",
    "id": 179926
  },
  {
    "lat": 45.651355556,
    "lon": -122.741147222,
    "name": "TTIDE KPDX K1",
    "id": 179927
  },
  {
    "lat": 45.778566667,
    "lon": -122.680783333,
    "name": "VOODU KPDX K1",
    "id": 179928
  },
  {
    "lat": 45.703413889,
    "lon": -122.900991667,
    "name": "WETTR KPDX K1",
    "id": 179929
  },
  {
    "lat": 45.395983333,
    "lon": -122.511113889,
    "name": "WIDMR KPDX K1",
    "id": 179930
  },
  {
    "lat": 45.559866667,
    "lon": -122.506072222,
    "name": "WUGPU KPDX K1",
    "id": 179931
  },
  {
    "lat": 45.564202778,
    "lon": -122.504488889,
    "name": "YANNO KPDX K1",
    "id": 179932
  },
  {
    "lat": 45.555427778,
    "lon": -122.519611111,
    "name": "YINUP KPDX K1",
    "id": 179933
  },
  {
    "lat": 45.748663889,
    "lon": -122.378830556,
    "name": "YIPYU KPDX K1",
    "id": 179934
  },
  {
    "lat": 45.711355556,
    "lon": -122.652994444,
    "name": "YORKY KPDX K1",
    "id": 179935
  },
  {
    "lat": 45.647872222,
    "lon": -122.595516667,
    "name": "ZOLIL KPDX K1",
    "id": 179936
  },
  {
    "lat": 45.973916667,
    "lon": -122.920227778,
    "name": "COVHO KSPB K1",
    "id": 185211
  },
  {
    "lat": 45.868219444,
    "lon": -122.889747222,
    "name": "EDUME KSPB K1",
    "id": 185212
  },
  {
    "lat": 45.966402778,
    "lon": -122.918055556,
    "name": "EXRAY KSPB K1",
    "id": 185213
  },
  {
    "lat": 45.834641667,
    "lon": -122.880094444,
    "name": "HOXIB KSPB K1",
    "id": 185214
  },
  {
    "lat": 45.892244444,
    "lon": -122.896663889,
    "name": "ISRIY KSPB K1",
    "id": 185216
  },
  {
    "lat": 45.888975,
    "lon": -122.895722222,
    "name": "RIXUQ KSPB K1",
    "id": 185217
  },
  {
    "lat": 45.869302778,
    "lon": -122.890058333,
    "name": "WESAV KSPB K1",
    "id": 185218
  },
  {
    "lat": 45.833436111,
    "lon": -122.879741667,
    "name": "ZIRBA KSPB K1",
    "id": 185219
  },
  {
    "lat": 45.545733333,
    "lon": -122.404736111,
    "name": "APACE KTTD K1",
    "id": 186991
  },
  {
    "lat": 45.499286111,
    "lon": -122.450997222,
    "name": "FAIYR KTTD K1",
    "id": 186992
  },
  {
    "lat": 45.705277778,
    "lon": -122.5,
    "name": "MILLL KTTD K1",
    "id": 186993
  },
  {
    "lat": 45.3762,
    "lon": -122.540813889,
    "name": "SSHAM KTTD K1",
    "id": 186994
  },
  {
    "lat": 45.463333333,
    "lon": -122.486836111,
    "name": "WOODD KTTD K1",
    "id": 186995
  },
  {
    "lat": 45.165311111,
    "lon": -122.784536111,
    "name": "CIGRU KUAO K1",
    "id": 187402
  },
  {
    "lat": 45.032961111,
    "lon": -122.807886111,
    "name": "DUBMY KUAO K1",
    "id": 187403
  },
  {
    "lat": 45.294405556,
    "lon": -122.86355,
    "name": "EMILL KUAO K1",
    "id": 187405
  },
  {
    "lat": 45.288011111,
    "lon": -122.762794444,
    "name": "FIDOV KUAO K1",
    "id": 187406
  },
  {
    "lat": 45.107436111,
    "lon": -122.794758333,
    "name": "HITAK KUAO K1",
    "id": 187407
  },
  {
    "lat": 45.248505556,
    "lon": -122.774444444,
    "name": "HOMEN KUAO K1",
    "id": 187408
  },
  {
    "lat": 45.368994444,
    "lon": -122.748394444,
    "name": "LUTZZ KUAO K1",
    "id": 187409
  },
  {
    "lat": 45.468197222,
    "lon": -122.730708333,
    "name": "MOKIY KUAO K1",
    "id": 187410
  },
  {
    "lat": 45.274766667,
    "lon": -122.825405556,
    "name": "REYTO KUAO K1",
    "id": 187411
  },
  {
    "lat": 45.323827778,
    "lon": -122.920827778,
    "name": "WULAS KUAO K1",
    "id": 187412
  },
  {
    "lat": 45.621141667,
    "lon": -122.663294444,
    "name": "QEHBY KVUO K1",
    "id": 188289
  },
  {
    "lat": 45.635605556,
    "lon": -122.700536111,
    "name": "ZEZJI KVUO K1",
    "id": 188290
  }
]