[
  {
    "lat": 29.181944444,
    "lon": -106.138888889,
    "name": "COBRE ENRT MM",
    "id": 76452
  },
  {
    "lat": 29.211388889,
    "lon": -106.019166667,
    "name": "MINAS ENRT MM",
    "id": 77160
  },
  {
    "lat": 29.101388889,
    "lon": -106.143055556,
    "name": "ONGIV ENRT MM",
    "id": 77337
  },
  {
    "lat": 29.130277778,
    "lon": -106.023333333,
    "name": "ULURO ENRT MM",
    "id": 77838
  },
  {
    "lat": 29.486,
    "lon": -106.328902778,
    "name": "CU328 MMCU MM",
    "id": 79303
  },
  {
    "lat": 29.625916667,
    "lon": -106.087355556,
    "name": "CU341 MMCU MM",
    "id": 79304
  },
  {
    "lat": 29.544025,
    "lon": -106.088613889,
    "name": "CU343 MMCU MM",
    "id": 79305
  },
  {
    "lat": 29.014366667,
    "lon": -106.005188889,
    "name": "D343R MMCU MM",
    "id": 79337
  }
]