[
  {
    "type": 1,
    "icao": "KMTJ",
    "lat": 38.5087386175,
    "lon": -107.89452155250001,
    "communications": [],
    "elevation": 5758,
    "tower": false,
    "name": "Montrose Regional",
    "runways": [
      {
        "type": 100,
        "width": 30.48,
        "surfaceType": null,
        "numberStart": "13",
        "numberEnd": "31",
        "latStart": 38.50921265,
        "lonStart": -107.90487403,
        "latEnd": 38.49355274,
        "lonEnd": -107.88780531,
        "length": 0,
        "surfacetype": 1
      },
      {
        "type": 100,
        "width": 45.72,
        "surfaceType": null,
        "numberStart": "17",
        "numberEnd": "35",
        "latStart": 38.52982082,
        "lonStart": -107.89275755,
        "latEnd": 38.50236826,
        "lonEnd": -107.89264932,
        "length": 0,
        "surfacetype": 1
      }
    ],
    "id": 3012
  },
  {
    "type": 1,
    "icao": "1CO4",
    "lat": 38.57498555,
    "lon": -107.95895389,
    "communications": [],
    "elevation": 5560,
    "tower": false,
    "name": "Clifford Field",
    "runways": [
      {
        "type": 100,
        "width": 30.48,
        "surfaceType": null,
        "numberStart": "17",
        "numberEnd": "35",
        "latStart": 38.57950527,
        "lonStart": -107.95865091,
        "latEnd": 38.57046583,
        "lonEnd": -107.95925687,
        "length": 0,
        "surfacetype": 4
      }
    ],
    "id": 6347
  },
  {
    "type": 1,
    "icao": "3CO1",
    "lat": 38.84831638,
    "lon": -107.833395,
    "communications": [],
    "elevation": 6459,
    "tower": false,
    "name": "Cridler Field",
    "runways": [
      {
        "type": 100,
        "width": 24.38,
        "surfaceType": null,
        "numberStart": "05",
        "numberEnd": "23",
        "latStart": 38.8466423,
        "lonStart": -107.83743768,
        "latEnd": 38.84999046,
        "lonEnd": -107.82935232,
        "length": 0,
        "surfacetype": 4
      }
    ],
    "id": 7480
  },
  {
    "type": 1,
    "icao": "5CO1",
    "lat": 38.83331638,
    "lon": -107.85895112,
    "communications": [],
    "elevation": 6200,
    "tower": false,
    "name": "Shipman Ranch",
    "runways": [
      {
        "type": 100,
        "width": 33.53,
        "surfaceType": null,
        "numberStart": "02",
        "numberEnd": "20",
        "latStart": 38.82986569,
        "lonStart": -107.86182786,
        "latEnd": 38.83676707,
        "lonEnd": -107.85607438,
        "length": 0,
        "surfacetype": 3
      }
    ],
    "id": 8534
  },
  {
    "type": 1,
    "icao": "6CO2",
    "lat": 38.961111110000004,
    "lon": -107.95777778,
    "communications": [],
    "elevation": 7200,
    "tower": false,
    "name": "Mesawood Airpark",
    "runways": [
      {
        "type": 100,
        "width": 18.29,
        "surfaceType": null,
        "numberStart": "16",
        "numberEnd": "34",
        "latStart": 38.96437065,
        "lonStart": -107.95836692,
        "latEnd": 38.95785157,
        "lonEnd": -107.95718864,
        "length": 0,
        "surfacetype": 3
      }
    ],
    "id": 9036
  },
  {
    "type": 17,
    "icao": "6CO5",
    "lat": 38.45831305,
    "lon": -107.86774639,
    "communications": [],
    "elevation": 5858,
    "tower": false,
    "name": "[H] Montrose Blm",
    "runways": [
      {
        "type": 102,
        "width": 4.6,
        "surfaceType": 2,
        "numberStart": "H1",
        "numberEnd": null,
        "latStart": 38.45831305,
        "lonStart": -107.86774639,
        "latEnd": null,
        "lonEnd": null,
        "length": 4.6
      }
    ],
    "id": 9039
  },
  {
    "type": 17,
    "icao": "6CO8",
    "lat": 38.46609749,
    "lon": -107.87339584,
    "communications": [],
    "elevation": 5825,
    "tower": false,
    "name": "[H] West Area Pwr Admin Ops Center",
    "runways": [
      {
        "type": 102,
        "width": 18.3,
        "surfaceType": 1,
        "numberStart": "H1",
        "numberEnd": null,
        "latStart": 38.46609749,
        "lonStart": -107.87339584,
        "latEnd": null,
        "lonEnd": null,
        "length": 18.3
      }
    ],
    "id": 9042
  },
  {
    "type": 1,
    "icao": "7CO2",
    "lat": 38.84164944,
    "lon": -107.87561862,
    "communications": [],
    "elevation": 6200,
    "tower": false,
    "name": "Hawkins Ranch",
    "runways": [
      {
        "type": 100,
        "width": 15.24,
        "surfaceType": null,
        "numberStart": "18",
        "numberEnd": "36",
        "latStart": 38.83817496,
        "lonStart": -107.87664849,
        "latEnd": 38.84512392,
        "lonEnd": -107.87458875,
        "length": 0,
        "surfacetype": 4
      }
    ],
    "id": 9543
  },
  {
    "type": 1,
    "icao": "7V2",
    "lat": 38.831654,
    "lon": -107.645892,
    "communications": [
      {
        "type": 51,
        "frequency": 12270,
        "name": "CTAF/UNICOM"
      }
    ],
    "elevation": 5797,
    "tower": false,
    "name": "NORTH FORK VALLEY",
    "runways": [
      {
        "type": 100,
        "width": 18.29,
        "surfaceType": null,
        "numberStart": "05",
        "numberEnd": "23",
        "latStart": 38.8287,
        "lonStart": -107.652828,
        "latEnd": 38.834608,
        "lonEnd": -107.638956,
        "length": 0,
        "surfacetype": 1
      }
    ],
    "id": 9920
  },
  {
    "type": 1,
    "icao": "8CO5",
    "lat": 38.83387194,
    "lon": -107.89228612,
    "communications": [],
    "elevation": 6020,
    "tower": false,
    "name": "Widner",
    "runways": [
      {
        "type": 100,
        "width": 15.24,
        "surfaceType": null,
        "numberStart": "04",
        "numberEnd": "22",
        "latStart": 38.8320561,
        "lonStart": -107.89537958,
        "latEnd": 38.83568778,
        "lonEnd": -107.88919266,
        "length": 0,
        "surfacetype": 5
      }
    ],
    "id": 10016
  },
  {
    "type": 17,
    "icao": "31CO",
    "lat": 38.48054194,
    "lon": -107.86895084,
    "communications": [],
    "elevation": 5812,
    "tower": false,
    "name": "[H] Montrose Memorial Hospital",
    "runways": [
      {
        "type": 102,
        "width": 9.1,
        "surfaceType": 3,
        "numberStart": "H1",
        "numberEnd": null,
        "latStart": 38.48054194,
        "lonStart": -107.86895084,
        "latEnd": null,
        "lonEnd": null,
        "length": 9.1
      }
    ],
    "id": 11733
  },
  {
    "type": 1,
    "icao": "44CO",
    "lat": 38.83665,
    "lon": -107.79283806000001,
    "communications": [],
    "elevation": 6100,
    "tower": false,
    "name": "Redlands",
    "runways": [
      {
        "type": 100,
        "width": 24.38,
        "surfaceType": null,
        "numberStart": "16",
        "numberEnd": "34",
        "latStart": 38.84024375,
        "lonStart": -107.79340455,
        "latEnd": 38.83305625,
        "lonEnd": -107.79227157,
        "length": 0,
        "surfacetype": 5
      }
    ],
    "id": 12243
  },
  {
    "type": 1,
    "icao": "64CO",
    "lat": 38.41665361,
    "lon": -107.90061889,
    "communications": [],
    "elevation": 6200,
    "tower": false,
    "name": "Happy Canyon Aero Ranch",
    "runways": [
      {
        "type": 100,
        "width": 15.24,
        "surfaceType": null,
        "numberStart": "18",
        "numberEnd": "36",
        "latStart": 38.4209299,
        "lonStart": -107.89935885,
        "latEnd": 38.41237732,
        "lonEnd": -107.90187893,
        "length": 0,
        "surfacetype": 4
      }
    ],
    "id": 13022
  },
  {
    "type": 1,
    "icao": "73CO",
    "lat": 38.38887611,
    "lon": -107.82311612000001,
    "communications": [],
    "elevation": 6120,
    "tower": false,
    "name": "Woods",
    "runways": [
      {
        "type": 100,
        "width": 9.14,
        "surfaceType": null,
        "numberStart": "13",
        "numberEnd": "31",
        "latStart": 38.39106675,
        "lonStart": -107.82522219,
        "latEnd": 38.38668547,
        "lonEnd": -107.82101005,
        "length": 0,
        "surfacetype": 3
      }
    ],
    "id": 13385
  },
  {
    "type": 17,
    "icao": "94CO",
    "lat": 38.08471444,
    "lon": -107.70089306,
    "communications": [],
    "elevation": 7250,
    "tower": false,
    "name": "[H] Ponderosa",
    "runways": [
      {
        "type": 102,
        "width": 6.1,
        "surfaceType": 1,
        "numberStart": "H1",
        "numberEnd": null,
        "latStart": 38.08471444,
        "lonStart": -107.70089306,
        "latEnd": null,
        "lonEnd": null,
        "length": 6.1
      }
    ],
    "id": 14151
  },
  {
    "type": 1,
    "icao": "99V",
    "lat": 38.70393875,
    "lon": -107.6443775,
    "communications": [
      {
        "type": 51,
        "frequency": 12280,
        "name": "CTAF/UNICOM"
      }
    ],
    "elevation": 6470,
    "tower": false,
    "name": "CRAWFORD",
    "runways": [
      {
        "type": 100,
        "width": 6.1,
        "surfaceType": null,
        "numberStart": "07",
        "numberEnd": "25",
        "latStart": 38.703056,
        "lonStart": -107.6525,
        "latEnd": 38.705172,
        "lonEnd": -107.635544,
        "length": 0,
        "surfacetype": 1
      },
      {
        "type": 100,
        "width": 38.1,
        "surfaceType": null,
        "numberStart": "07R",
        "numberEnd": "25L",
        "latStart": 38.703208,
        "lonStart": -107.649069,
        "latEnd": 38.704319,
        "lonEnd": -107.640397,
        "length": 0,
        "surfacetype": 4
      }
    ],
    "id": 14345
  },
  {
    "type": 17,
    "icao": "CD29",
    "lat": 38.44998722,
    "lon": -107.65061389,
    "communications": [],
    "elevation": 8208,
    "tower": false,
    "name": "[H] Cerro Summit",
    "runways": [
      {
        "type": 102,
        "width": 30.5,
        "surfaceType": 3,
        "numberStart": "H1",
        "numberEnd": null,
        "latStart": 38.44998722,
        "lonStart": -107.65061389,
        "latEnd": null,
        "lonEnd": null,
        "length": 30.5
      }
    ],
    "id": 15144
  },
  {
    "type": 17,
    "icao": "CD30",
    "lat": 38.38332416,
    "lon": -107.41728028,
    "communications": [],
    "elevation": 9314,
    "tower": false,
    "name": "[H] Fitzpatrick",
    "runways": [
      {
        "type": 102,
        "width": 30.5,
        "surfaceType": 4,
        "numberStart": "H1",
        "numberEnd": null,
        "latStart": 38.38332416,
        "lonStart": -107.41728028,
        "latEnd": null,
        "lonEnd": null,
        "length": 30.5
      }
    ],
    "id": 15145
  },
  {
    "type": 1,
    "icao": "CO20",
    "lat": 38.86248277,
    "lon": -107.82145,
    "communications": [],
    "elevation": 6885,
    "tower": false,
    "name": "Flying W Ranch",
    "runways": [
      {
        "type": 100,
        "width": 15.24,
        "surfaceType": null,
        "numberStart": "17",
        "numberEnd": "35",
        "latStart": 38.86576984,
        "lonStart": -107.82122876,
        "latEnd": 38.8591957,
        "lonEnd": -107.82167124,
        "length": 0,
        "surfacetype": 3
      }
    ],
    "id": 15490
  },
  {
    "type": 1,
    "icao": "CO68",
    "lat": 38.053611110000006,
    "lon": -107.98277777999999,
    "communications": [],
    "elevation": 9580,
    "tower": false,
    "name": "Wilson Ranch",
    "runways": [
      {
        "type": 100,
        "width": 22.86,
        "surfaceType": null,
        "numberStart": "12",
        "numberEnd": "30",
        "latStart": 38.05498767,
        "lonStart": -107.98471931,
        "latEnd": 38.05223455,
        "lonEnd": -107.98083625,
        "length": 0,
        "surfacetype": 3
      }
    ],
    "id": 15529
  },
  {
    "type": 1,
    "icao": "CO76",
    "lat": 38.83637194,
    "lon": -107.86589639,
    "communications": [],
    "elevation": 6150,
    "tower": false,
    "name": "Eden Ranch",
    "runways": [
      {
        "type": 100,
        "width": 30.48,
        "surfaceType": null,
        "numberStart": "18",
        "numberEnd": "36",
        "latStart": 38.84038096,
        "lonStart": -107.86470817,
        "latEnd": 38.83236292,
        "lonEnd": -107.86708461,
        "length": 0,
        "surfacetype": 4
      }
    ],
    "id": 15536
  }
]