[
  {
    "id": 3262,
    "type": 2,
    "lat": -45.496942,
    "lon": 167.718322,
    "elevation": 687,
    "frequency": 346,
    "range": 40,
    "icao": null,
    "identifier": "MO",
    "runwayNumber": null,
    "name": "MANAPOURI NDB/DME",
    "variation": null,
    "bearing": 0,
    "bias": 0
  },
  {
    "id": 26514,
    "type": 13,
    "lat": -45.496942,
    "lon": 167.718322,
    "elevation": 687,
    "frequency": 11780,
    "range": 40,
    "icao": null,
    "identifier": null,
    "runwayNumber": null,
    "name": null,
    "variation": null,
    "bearing": 0,
    "bias": 0
  }
]