[
  {
    "id": 8475,
    "type": 3,
    "lat": 45.623333,
    "lon": 126.26,
    "elevation": 448,
    "frequency": 11250,
    "range": 130,
    "icao": null,
    "identifier": "HRB",
    "runwayNumber": null,
    "name": "HARBIN VOR/DME",
    "variation": -10.2,
    "bearing": 0,
    "bias": 0
  },
  {
    "id": 14103,
    "type": 4,
    "lat": 45.636283,
    "lon": 126.265356,
    "elevation": 456,
    "frequency": 11030,
    "range": 18,
    "icao": "ZYHB",
    "identifier": "ILL",
    "runwayNumber": "05",
    "name": "ILS-cat-I",
    "variation": null,
    "bearing": 39.259,
    "bias": 0
  },
  {
    "id": 14104,
    "type": 4,
    "lat": 45.610169,
    "lon": 126.234894,
    "elevation": 456,
    "frequency": 10990,
    "range": 18,
    "icao": "ZYHB",
    "identifier": "IMJ",
    "runwayNumber": "23",
    "name": "ILS-cat-I",
    "variation": null,
    "bearing": 219.233,
    "bias": 0
  },
  {
    "id": 17607,
    "type": 6,
    "lat": 45.613819,
    "lon": 126.24105,
    "elevation": 456,
    "frequency": 11030,
    "range": 10,
    "icao": "ZYHB",
    "identifier": "ILL",
    "runwayNumber": "05",
    "name": "GS",
    "variation": null,
    "bearing": 300039.29,
    "bias": 0
  },
  {
    "id": 17608,
    "type": 6,
    "lat": 45.631808,
    "lon": 126.262036,
    "elevation": 456,
    "frequency": 10990,
    "range": 10,
    "icao": "ZYHB",
    "identifier": "IMJ",
    "runwayNumber": "23",
    "name": "GS",
    "variation": null,
    "bearing": 300219.29,
    "bias": 0
  },
  {
    "id": 23906,
    "type": 12,
    "lat": 45.623333,
    "lon": 126.26,
    "elevation": 448,
    "frequency": 11250,
    "range": 130,
    "icao": null,
    "identifier": null,
    "runwayNumber": null,
    "name": null,
    "variation": null,
    "bearing": 0,
    "bias": 0
  }
]