[
  {
    "lat": 45.300008333,
    "lon": -65.296141667,
    "name": "CAAPE ENRT CY",
    "id": 11139
  },
  {
    "lat": 45.857777778,
    "lon": -65.909166667,
    "name": "NOSUL CYFC CY",
    "id": 16322
  },
  {
    "lat": 45.800213889,
    "lon": -65.093830556,
    "name": "QM640 CYQM CY",
    "id": 18693
  },
  {
    "lat": 45.287022222,
    "lon": -65.798244444,
    "name": "AGDEL CYSJ CY",
    "id": 19307
  },
  {
    "lat": 45.165997222,
    "lon": -65.479752778,
    "name": "ALVIM CYSJ CY",
    "id": 19308
  },
  {
    "lat": 45.163788889,
    "lon": -65.737069444,
    "name": "BALFE CYSJ CY",
    "id": 19309
  },
  {
    "lat": 45.313605556,
    "lon": -65.368055556,
    "name": "BEVIX CYSJ CY",
    "id": 19310
  },
  {
    "lat": 45.329905556,
    "lon": -65.899483333,
    "name": "BIPDO CYSJ CY",
    "id": 19311
  },
  {
    "lat": 45.534297222,
    "lon": -65.696466667,
    "name": "BOOTI CYSJ CY",
    "id": 19312
  },
  {
    "lat": 45.364647222,
    "lon": -65.981819444,
    "name": "CHATH CYSJ CY",
    "id": 19313
  },
  {
    "lat": 45.306491667,
    "lon": -65.615275,
    "name": "CYPTI CYSJ CY",
    "id": 19315
  },
  {
    "lat": 45.560861111,
    "lon": -65.728716667,
    "name": "D050K CYSJ CY",
    "id": 19317
  },
  {
    "lat": 45.512158333,
    "lon": -65.657269444,
    "name": "D072K CYSJ CY",
    "id": 19318
  },
  {
    "lat": 45.542397222,
    "lon": -65.694863889,
    "name": "D229K CYSJ CY",
    "id": 19321
  },
  {
    "lat": 45.113197222,
    "lon": -65.917988889,
    "name": "DASGU CYSJ CY",
    "id": 19322
  },
  {
    "lat": 45.235155556,
    "lon": -65.676247222,
    "name": "DUGVO CYSJ CY",
    "id": 19323
  },
  {
    "lat": 45.276027778,
    "lon": -65.917216667,
    "name": "EBDAK CYSJ CY",
    "id": 19324
  },
  {
    "lat": 45.299555556,
    "lon": -65.827802778,
    "name": "GABLO CYSJ CY",
    "id": 19326
  },
  {
    "lat": 45.360688889,
    "lon": -65.619236111,
    "name": "GOXOS CYSJ CY",
    "id": 19327
  },
  {
    "lat": 45.575902778,
    "lon": -65.972813889,
    "name": "IRLES CYSJ CY",
    "id": 19329
  },
  {
    "lat": 45.2418,
    "lon": -65.946288889,
    "name": "KAVKA CYSJ CY",
    "id": 19332
  },
  {
    "lat": 45.549938889,
    "lon": -65.957072222,
    "name": "OTRAN CYSJ CY",
    "id": 19333
  },
  {
    "lat": 45.373830556,
    "lon": -65.833913889,
    "name": "PELPU CYSJ CY",
    "id": 19335
  },
  {
    "lat": 45.507916667,
    "lon": -65.857477778,
    "name": "PIBMI CYSJ CY",
    "id": 19336
  },
  {
    "lat": 45.286725,
    "lon": -65.797541667,
    "name": "SEBER CYSJ CY",
    "id": 19338
  },
  {
    "lat": 45.421880556,
    "lon": -65.654675,
    "name": "SUXIP CYSJ CY",
    "id": 19339
  },
  {
    "lat": 45.464944444,
    "lon": -65.756,
    "name": "TAKOG CYSJ CY",
    "id": 19340
  },
  {
    "lat": 45.379294444,
    "lon": -65.829247222,
    "name": "UDGUN CYSJ CY",
    "id": 19341
  },
  {
    "lat": 45.365505556,
    "lon": -65.983852778,
    "name": "XULDA CYSJ CY",
    "id": 19342
  },
  {
    "lat": 45.202533333,
    "lon": -65.032455556,
    "name": "BUBOT CYZX CY",
    "id": 21637
  },
  {
    "lat": 45.166961111,
    "lon": -65.081869444,
    "name": "OVIPI CYZX CY",
    "id": 21660
  },
  {
    "lat": 45.068011111,
    "lon": -65.166402778,
    "name": "PILDI CYZX CY",
    "id": 21666
  },
  {
    "lat": 45.013991667,
    "lon": -65.215691667,
    "name": "TOVUK CYZX CY",
    "id": 21686
  }
]