[
  {
    "id": 1876,
    "type": 12,
    "lat": 46.777583333,
    "lon": 7.2235,
    "elevation": 2659,
    "frequency": 11085,
    "range": 40,
    "icao": "ENRT",
    "identifier": "FRI",
    "runwayNumber": "LS",
    "name": "FRIBOURG VOR/DME",
    "variation": null,
    "bearing": 0,
    "bias": 0
  },
  {
    "id": 2235,
    "type": 12,
    "lat": 46.2155,
    "lon": 7.288777778,
    "elevation": 1594,
    "frequency": 11215,
    "range": 130,
    "icao": "ENRT",
    "identifier": "SIO",
    "runwayNumber": "LS",
    "name": "SION VOR/DME",
    "variation": null,
    "bearing": 0,
    "bias": 0
  },
  {
    "id": 3024,
    "type": 12,
    "lat": 46.215194444,
    "lon": 7.312833333,
    "elevation": 1609,
    "frequency": 11070,
    "range": 25,
    "icao": "LSGS",
    "identifier": "ISI",
    "runwayNumber": "LS",
    "name": "SION DME-ILS",
    "variation": null,
    "bearing": 0,
    "bias": 0
  },
  {
    "id": 3030,
    "type": 12,
    "lat": 46.906111111,
    "lon": 7.50575,
    "elevation": 1684,
    "frequency": 11010,
    "range": 25,
    "icao": "LSZB",
    "identifier": "IBE",
    "runwayNumber": "LS",
    "name": "BELP DME-ILS",
    "variation": null,
    "bearing": 0,
    "bias": 0
  }
]